envolved/__init__.py
envolved/_version.py
envolved/absolute_name.py
envolved/basevar.py
envolved/describe/__init__.py
envolved/describe/flat.py
envolved/describe/nested.py
envolved/describe/util.py
envolved/envparser.py
envolved/envvar.py
envolved/exceptions.py
envolved/factory_spec.py
envolved/infer_env_var.py
envolved/parsers.py
envolved/py.typed
envolved/utils.py
envolved-1.7.0.dist-info/LICENSE
envolved-1.7.0.dist-info/METADATA
envolved-1.7.0.dist-info/WHEEL
envolved-1.7.0.dist-info/RECORD
