Metadata-Version: 2.1
Name: envolved
Version: 1.7.0
Summary: 
Home-page: https://github.com/bentheiii/envolved
License: MIT
Author: ben avrahami
Author-email: avrahami.ben@gmail.com
Requires-Python: >=3.8,<4.0
Classifier: License :: OSI Approved :: MIT License
Classifier: Programming Language :: Python :: 3
Classifier: Programming Language :: Python :: 3.8
Classifier: Programming Language :: Python :: 3.9
Classifier: Programming Language :: Python :: 3.10
Classifier: Programming Language :: Python :: 3.11
Classifier: Programming Language :: Python :: 3.12
Requires-Dist: typing-extensions
Project-URL: Repository, https://github.com/bentheiii/envolved
